{
    "Filename": "0010039",
    "Imagepath": "C:/Users/Yhc/Desktop/slice/augmentation/Images/0010039.jpg",
    "OutputImagepath": "",
    "Human_ids_path": "C:/Users/Yhc/Desktop/slice/augmentation/Human_ids/0010039.png",
    "Humansimg_path": "",
    "Category_ids_path": "C:/Users/Yhc/Desktop/slice/augmentation/Category_ids/0010039.png",
    "Categoriesimg_path": "",
    "Instance_ids_path": "C:/Users/Yhc/Desktop/slice/augmentation/Instance_ids/0010039.png",
    "Instancesimg_path": "",
    "Is_train": true,
    "Is_val": false,
    "Is_test": false,
    "Resolution": [
        375,
        500
    ],
    "IoU": 0.03482779916691852,
    "Instance_number": 2,
    "Visible_Parsing": 2,
    "Parts_number": 10,
    "Parts": [
        0,
        2,
        6,
        8,
        10,
        13,
        14,
        15,
        16,
        17
    ],
    "Keypoints_number": 17,
    "Visible_keypoints_number": 0,
    "Visible_keypoints_type": [],
    "Visible_keypoints_type_number": 0,
    "Visible_Pose": 0,
    "Instances": {
        "Instance1": {
            "Instance_name": "Instance1",
            "Has_parsing": true,
            "Bbox": [
                0,
                273,
                48,
                327
            ],
            "BboxResolution": [
                273,
                279
            ],
            "SegmentationResolution": 36241,
            "BboxScale": 0.406224,
            "IoU": 0.03482779916691852,
            "SegmentationScale": 0.19328533333333334,
            "Parts_number": 9,
            "Parts": [
                2,
                6,
                8,
                10,
                13,
                14,
                15,
                16,
                17
            ],
            "Poses_of_predicted_number": 3,
            "Poses_of_predicted": {
                "Pose1": {
                    "Model": "SP",
                    "Keypoints": [
                        162.996261,
                        139.018912,
                        181.960288,
                        123.034931,
                        149.96152,
                        125.043558,
                        218.995817,
                        123.97533,
                        134.998068,
                        131.017204,
                        234.018214,
                        167.023825,
                        136.998915,
                        181.99768,
                        249.98148,
                        210.988053,
                        145.99925,
                        248.012654,
                        246.019661,
                        251.007178,
                        176.00034,
                        282.016832,
                        185.001786,
                        249.99593,
                        118.003218,
                        237.002147,
                        226.002303,
                        265.99928,
                        70.994959,
                        270.005345,
                        203.992436,
                        268.999652,
                        7.003314,
                        302.001537
                    ]
                },
                "Pose2": {
                    "Model": "PL",
                    "Keypoints": [
                        132.0,
                        107.0,
                        0.0196,
                        109.0,
                        155.0,
                        0.016708,
                        113.0,
                        208.0,
                        0.003921,
                        141.0,
                        222.0,
                        0.0083,
                        191.0,
                        136.0,
                        0.00701,
                        199.0,
                        187.0,
                        0.002543,
                        202.0,
                        204.0,
                        0.001451,
                        150.0,
                        244.0,
                        0.001198,
                        0.0,
                        0.0,
                        0.0,
                        0.0,
                        0.0,
                        0.0,
                        190.0,
                        224.0,
                        0.001806,
                        0.0,
                        0.0,
                        0.0,
                        0.0,
                        0.0,
                        0.0,
                        120.0,
                        97.0,
                        0.015512,
                        144.0,
                        95.0,
                        0.016842,
                        109.0,
                        105.0,
                        0.004242,
                        175.0,
                        98.0,
                        0.010777
                    ]
                },
                "Pose3": {
                    "Model": "HHR",
                    "Keypoints": [
                        163.02490234375,
                        138.37841796875,
                        0.7489327192306519,
                        182.43408203125,
                        121.89892578125,
                        0.813093364238739,
                        150.93994140625,
                        124.09619140625,
                        0.7989667654037476,
                        219.05517578125,
                        124.46240234375,
                        0.7165085673332214,
                        135.55908203125,
                        131.05419921875,
                        0.18528008460998535,
                        236.26708984375,
                        167.67529296875,
                        0.46070799231529236,
                        139.22119140625,
                        183.78857421875,
                        0.39614376425743103,
                        250.54931640625,
                        210.52197265625,
                        0.6884434819221497,
                        147.27783203125,
                        246.77685546875,
                        0.6929784417152405,
                        246.88720703125,
                        252.63623046875,
                        0.5905545949935913,
                        176.57470703125,
                        280.83447265625,
                        0.6443425416946411,
                        212.46337890625,
                        253.73486328125,
                        0.2287335842847824,
                        135.92529296875,
                        256.29833984375,
                        0.08796652406454086,
                        240.29541015625,
                        263.25634765625,
                        0.0459524504840374,
                        71.10595703125,
                        267.28466796875,
                        0.3295246958732605,
                        200.37841796875,
                        273.87646484375,
                        0.06128566712141037,
                        14.70947265625,
                        297.68017578125,
                        0.19326630234718323
                    ]
                }
            },
            "Has_gtpose": false,
            "Gtpose": {}
        },
        "Instance2": {
            "Instance_name": "Instance2",
            "Has_parsing": true,
            "Bbox": [
                254,
                499,
                0,
                332
            ],
            "BboxResolution": [
                245,
                332
            ],
            "SegmentationResolution": 40485,
            "BboxScale": 0.43381333333333333,
            "IoU": 0.03482779916691852,
            "SegmentationScale": 0.21592,
            "Parts_number": 9,
            "Parts": [
                2,
                6,
                8,
                10,
                13,
                14,
                15,
                16,
                17
            ],
            "Poses_of_predicted_number": 3,
            "Poses_of_predicted": {
                "Pose1": {
                    "Model": "SP",
                    "Keypoints": [
                        347.004523,
                        76.041029,
                        362.937377,
                        63.988222,
                        331.017077,
                        63.951306,
                        383.997181,
                        72.012399,
                        305.995218,
                        74.975443,
                        391.998888,
                        122.022004,
                        291.982719,
                        119.004554,
                        396.016023,
                        182.013252,
                        282.988766,
                        182.977763,
                        382.994708,
                        240.018337,
                        308.016401,
                        234.017732,
                        369.002948,
                        226.008212,
                        316.999091,
                        232.000663,
                        412.992413,
                        223.002399,
                        306.999026,
                        260.998889,
                        454.001041,
                        266.989416,
                        312.999122,
                        293.009418
                    ]
                },
                "Pose2": {
                    "Model": "PL",
                    "Keypoints": [
                        349.1271820448878,
                        72.31920199501246,
                        0.025639650872817957,
                        289.27680798004985,
                        124.68827930174562,
                        0.01427930174563591,
                        281.7955112219451,
                        194.51371571072318,
                        0.0064925187032418945,
                        310.4738154613466,
                        243.14214463840398,
                        0.0048254364089775565,
                        392.76807980049875,
                        122.19451371571071,
                        0.018236907730673317,
                        385.286783042394,
                        215.71072319201994,
                        0.005809226932668329,
                        438.90274314214463,
                        263.09226932668327,
                        0.002098503740648379,
                        325.4364089775561,
                        244.38902743142143,
                        0.0016957605985037406,
                        0.0,
                        0.0,
                        0.0,
                        0.0,
                        0.0,
                        0.0,
                        366.58354114713217,
                        241.89526184538653,
                        0.001311720698254364,
                        0.0,
                        0.0,
                        0.0,
                        0.0,
                        0.0,
                        0.0,
                        331.6708229426434,
                        58.603491271820445,
                        0.026188279301745634,
                        361.5960099750623,
                        58.603491271820445,
                        0.02490523690773067,
                        304.23940149625935,
                        69.82543640897755,
                        0.015236907730673316,
                        377.80548628428926,
                        68.57855361596009,
                        0.010134663341645884
                    ]
                },
                "Pose3": {
                    "Model": "HHR",
                    "Keypoints": [
                        347.59521484375,
                        75.75634765625,
                        0.7827655673027039,
                        362.97607421875,
                        63.30517578125,
                        0.8255832195281982,
                        330.74951171875,
                        63.30517578125,
                        0.802623987197876,
                        384.21630859375,
                        72.82666015625,
                        0.4946174621582031,
                        305.11474609375,
                        77.22119140625,
                        0.533252477645874,
                        393.37158203125,
                        121.89892578125,
                        0.5037758946418762,
                        293.02978515625,
                        117.87060546875,
                        0.42470279335975647,
                        395.93505859375,
                        183.05615234375,
                        0.6589235067367554,
                        283.14208984375,
                        181.22509765625,
                        0.6720221638679504,
                        383.85009765625,
                        239.45263671875,
                        0.5918848514556885,
                        308.04443359375,
                        232.86083984375,
                        0.6439483165740967,
                        365.90576171875,
                        228.83251953125,
                        0.22801968455314636,
                        312.80517578125,
                        230.66357421875,
                        0.21731235086917877,
                        413.14697265625,
                        221.50830078125,
                        0.4569450914859772,
                        309.87548828125,
                        263.62255859375,
                        0.2014084756374359,
                        455.62744140625,
                        266.55224609375,
                        0.43300679326057434,
                        312.80517578125,
                        284.49658203125,
                        0.12772570550441742
                    ]
                }
            },
            "Has_gtpose": false,
            "Gtpose": {}
        }
    },
    "Delete": {
        "Is_deleted": false,
        "Reason": ""
    },
    "DataAugmentation": {
        "Has_Augmentation": {
            "Has_Augmentation": false,
            "Background_Augmentation": {
                "Has": false,
                "New_Imagepath": []
            },
            "Occlusion_Augmentation": {
                "Has": false,
                "New_Imagepath": []
            },
            "Part_Augmentation": {
                "Has": false,
                "New_Imagepath": []
            }
        },
        "Is_Augmentation": {
            "Is_Augmentation": true,
            "Type": "Crowd_Occlusion_Augmentation",
            "Original_Image": [
                [
                    26,
                    0,
                    0,
                    0
                ],
                [
                    24,
                    1,
                    -172,
                    -66
                ]
            ]
        }
    },
    "TestSet": {
        "In_Simple_Parts_Testset": false,
        "In_Normal_Parts_Testset": false,
        "In_Hard_Parts_Testset": false,
        "In_Not_Crowded_Testset": false,
        "In_Crowded_Testset": false,
        "In_Scatter_Testset": false,
        "In_Occlude_Testset": false
    },
    "Poses_Without_parsing": 0
}